adif_io/__init__.py
adif_io-0.6.1.dist-info/licenses/LICENSE
adif_io-0.6.1.dist-info/licenses/NOTICE
adif_io-0.6.1.dist-info/METADATA
adif_io-0.6.1.dist-info/WHEEL
adif_io-0.6.1.dist-info/top_level.txt
adif_io-0.6.1.dist-info/RECORD
