Metadata-Version: 2.4
Name: adif_io
Version: 0.6.1
Summary: Input and output of ADIF radio amateur log files.
Author-email: "Dr. Andreas Krüger, DJ3EI" <dj3ei@famsik.de>
Project-URL: Homepage, https://gitlab.com/andreas_krueger_py/adif_io
Project-URL: Repository, https://gitlab.com/andreas_krueger_py/adif_io
Project-URL: Issues, https://gitlab.com/andreas_krueger_py/adif_io/-/issues
Keywords: ham,amateur radio
Classifier: Programming Language :: Python :: 3
Classifier: License :: OSI Approved :: Apache Software License
Classifier: Operating System :: OS Independent
Classifier: Development Status :: 4 - Beta
Classifier: Intended Audience :: Developers
Classifier: Topic :: Communications :: Ham Radio
Requires-Python: >=3.10
License-File: LICENSE
License-File: NOTICE
Dynamic: license-file
